traceax/__init__.py
traceax/_estimators.py
traceax/_samplers.py
traceax/_version.py
traceax-1.0.2.dist-info/METADATA
traceax-1.0.2.dist-info/WHEEL
traceax-1.0.2.dist-info/licenses/LICENSE
traceax-1.0.2.dist-info/RECORD
