Metadata-Version: 2.4
Name: traceax
Version: 1.0.2
Summary: Stochastic trace estimation in JAX, Lineax, and Equinox
Project-URL: Documentation, https://github.com/mancusolab/traceax#readme
Project-URL: Issues, https://github.com/mancusolab/traceax/issues
Project-URL: Source, https://github.com/mancusolab/traceax
Author-email: Abdullah Al Nahid <alnahid@usc.edu>, Linda Serafin <lserafin@usc.edu>, Nicholas Mancuso <nmancuso@usc.edu>
License: Apache2.0
License-File: LICENSE
Keywords: jax,machine-learning,statistics,trace-estimation
Classifier: Development Status :: 4 - Beta
Classifier: Intended Audience :: Developers
Classifier: Intended Audience :: Science/Research
Classifier: License :: OSI Approved :: Apache Software License
Classifier: Natural Language :: English
Classifier: Programming Language :: Python
Classifier: Programming Language :: Python :: 3.9
Classifier: Programming Language :: Python :: 3.10
Classifier: Programming Language :: Python :: 3.11
Classifier: Programming Language :: Python :: 3.12
Classifier: Programming Language :: Python :: Implementation :: CPython
Classifier: Programming Language :: Python :: Implementation :: PyPy
Classifier: Topic :: Scientific/Engineering
Classifier: Topic :: Scientific/Engineering :: Artificial Intelligence
Classifier: Topic :: Scientific/Engineering :: Information Analysis
Classifier: Topic :: Scientific/Engineering :: Mathematics
Requires-Python: >=3.9
Requires-Dist: equinox>=0.11.3
Requires-Dist: jax>=0.4.13
Requires-Dist: jaxtyping>=0.2.20
Requires-Dist: lineax>=0.0.4
Requires-Dist: typing-extensions>=4.5.0
Provides-Extra: docs
Requires-Dist: hippogriffe; extra == 'docs'
Requires-Dist: mkdocs; extra == 'docs'
Requires-Dist: mkdocs-include-exclude-files; extra == 'docs'
Requires-Dist: mkdocs-material; extra == 'docs'
Requires-Dist: mkdocstrings-python; extra == 'docs'
Requires-Dist: mkdocstrings>=0.29.0; extra == 'docs'
Requires-Dist: pymdown-extensions; extra == 'docs'
